[
  {
    "id": 1,
    "kitOrSingle": 1,
    "brand": "Ludwig",
    "name": "Accent Series",
    "model": "LC17514",
    "numPieces": 8,
    "isElectric": false,
    "description": "5pc drum kit, wine red",
    "year": "1995",
    "countryOfOrigin": "China",
    "value": 450,
    "numDrums": 5,
    "numCymbals": 3,
    "skinsAreAftermarket": false,
    "brandOfSkins": null,
    "nameOfSkins": null,
    "cymbalsAreAftermarket": true,
    "brandOfCymbals": "Zildjan",
    "nameOfCymbals": "ZBT",
    "hasThrone": true,
    "brandOfThrone": "Ludwig",
    "nameOfThrone": "Orignial",
    "hasBassPillow": false,
    "brandOfBassPillow": null,
    "nameOfBassPillow": null,
    "image": "lud-accent-1.png"
  },
  {
    "id": 2,
    "kitOrSingle": 1,
    "brand": "Ludwig",
    "name": "Junior Series",
    "model": "LJR106",
    "numPieces": 8,
    "isElectric": false,
    "description": "5pc drum kit, kids size, blue",
    "year": "2016",
    "countryOfOrigin": "China",
    "value": 350,
    "numDrums": 5,
    "numCymbals": 3,
    "skinsAreAftermarket": false,
    "brandOfSkins": null,
    "nameOfSkins": null,
    "cymbalsAreAftermarket": true,
    "brandOfCymbals": "Meinl",
    "nameOfCymbals": "HCS",
    "hasThrone": true,
    "brandOfThrone": "Ludwig",
    "nameOfThrone": "Orignial",
    "hasBassPillow": false,
    "brandOfBassPillow": null,
    "nameOfBassPillow": null,
    "image": "ludwig-jr-kit.png"
  },
  {
    "id": 3,
    "kitOrSingle": 2,
    "brand": "Meinl",
    "name": "Wood Djembe",
    "model": "HDJ3-M",
    "numPieces": 1,
    "isElectric": false,
    "description": "10\" Rope Tuned Headliner Series Wood Djembe made from a solid piece of plantation grown Mahogany wood, and are hand carved with a horizontal ripple motif that suggests a flowing river. This also makes the djembe easy to grip between the knees. The hand selected goat skin head is secured and tuned with the traditional Mali Weave system.",
    "year": "2016",
    "countryOfOrigin": "Germany",
    "value": 80,
    "numDrums": 1,
    "numCymbals": 0,
    "skinsAreAftermarket": false,
    "brandOfSkins": null,
    "nameOfSkins": null,
    "cymbalsAreAftermarket": false,
    "brandOfCymbals": null,
    "nameOfCymbals": null,
    "hasThrone": null,
    "brandOfThrone": null,
    "nameOfThrone": null,
    "hasBassPillow": null,
    "brandOfBassPillow": null,
    "nameOfBassPillow": null,
    "image": "meinl-djembe-10.png"
  }
]
